LICENSE
README.md
setup.py
nxt/__init__.py
nxt/clean_json.py
nxt/cli.py
nxt/constants.py
nxt/legacy.py
nxt/nxt_io.py
nxt/nxt_layer.py
nxt/nxt_log.py
nxt/nxt_node.py
nxt/nxt_path.py
nxt/plugin_loader.py
nxt/runtime.py
nxt/session.py
nxt/stage.py
nxt/tokens.py
nxt/version.json
nxt/builtin/WidgetNodes.nxt
nxt/builtin/_context.nxt
nxt/builtin/remote_contexts.nxt
nxt/builtin/sub_graphs.nxt
nxt/plugins/__init__.py
nxt/plugins/example.py
nxt/plugins/file_fallbacks.py
nxt/remote/__init__.py
nxt/remote/blender_context.nxt
nxt/remote/client.py
nxt/remote/contexts.py
nxt/remote/maya_context.nxt
nxt/remote/nxt_socket.py
nxt/remote/remote_context_template.py
nxt/remote/server.py
nxt/test/FileTokenSub.nxt
nxt/test/LowerRespect.nxt
nxt/test/RelPathRef.nxt
nxt/test/ResolveNewlines.nxt
nxt/test/RuntimeProp.nxt
nxt/test/StageChildOrderTest.nxt
nxt/test/StageChildOrderTest_TopLayer.nxt
nxt/test/StageInheritTest.nxt
nxt/test/StageInheritTest_LowerLayer.nxt
nxt/test/StageInstanceAcrossLayersTest.nxt
nxt/test/StageInstanceTest.nxt
nxt/test/StageInstanceTest_Layer0.nxt
nxt/test/StageInstanceTest_Layer1.nxt
nxt/test/StageInstanceTest_Layer2.nxt
nxt/test/StageLoadTest.nxt
nxt/test/StageRelativeInstanceChildOrder.nxt
nxt/test/StageRuntimeScope.nxt
nxt/test/StageRuntimeTest1.nxt
nxt/test/StageRuntimeTest2.nxt
nxt/test/TokenSiblingTest.nxt
nxt/test/UpperLowerRespect.nxt
nxt/test/__init__.py
nxt/test/cli_test.nxt
nxt/test/empty.nxt
nxt/test/future_tokens_test.nxt
nxt/test/order.nxt
nxt/test/real_file.txt
nxt/test/ref_test.nxt
nxt/test/test_builtins.py
nxt/test/test_cli.py
nxt/test/test_inner_graph.nxt
nxt/test/test_layer.py
nxt/test/test_legacy.py
nxt/test/test_pathing.py
nxt/test/test_plugins.py
nxt/test/test_proxy_stack.nxt
nxt/test/test_resolve.py
nxt/test/test_spec_graphs.py
nxt/test/test_stage.py
nxt/test/test_sub_graph.nxt
nxt/test/test_sub_graph_exit.nxt
nxt/test/test_tokens.py
nxt/test/unittests.nxt
nxt/test/legacy/0.45.0_BottomLayer.nxt
nxt/test/legacy/0.45.0_TopLayer.nxt
nxt_core.egg-info/PKG-INFO
nxt_core.egg-info/SOURCES.txt
nxt_core.egg-info/dependency_links.txt
nxt_core.egg-info/entry_points.txt
nxt_core.egg-info/top_level.txt