Metadata-Version: 2.1
Name: nxt-core
Version: 0.17.0
Summary: A general purpose code compositor designed for rigging, scene assembly, and automation. (node execution tree)
Home-page: https://github.com/nxt-dev/nxt
Author: The nxt contributors
Author-email: dev@opennxt.dev
Requires-Python: >=3.7, <3.11
License-File: LICENSE
